uv4/__init__.py
uv4/constants.py
uv4/hook.py
uv4/liquidity.py
uv4/q_number.py
uv4/tickmath.py
uv4/utils.py
uv4-0.1.4.dist-info/METADATA
uv4-0.1.4.dist-info/WHEEL
uv4-0.1.4.dist-info/entry_points.txt
uv4-0.1.4.dist-info/RECORD
