Metadata-Version: 2.4
Name: uv4
Version: 0.1.4
Summary: python utilities for uniswap v4
Project-URL: Repository, https://github.com/mmsaki/uv4.git
Project-URL: Issues, https://github.com/mmsaki/uv4/issues
Author-email: Meek Msaki <98189596+mmsaki@users.noreply.github.com>
Requires-Python: >=3.9
Requires-Dist: eth-abi>=5.2.0
Requires-Dist: ipython>=8.18.1
Requires-Dist: pytest-cov>=6.0.0
Requires-Dist: pytest-watcher>=0.4.3
Requires-Dist: pytest>=8.3.4
